pytest_bashdoctest/__init__.py
pytest_bashdoctest/executor.py
pytest_bashdoctest/formatter.py
pytest_bashdoctest/matcher.py
pytest_bashdoctest/parser.py
pytest_bashdoctest/plugin.py
pytest_bashdoctest-2025.10.3.dist-info/METADATA
pytest_bashdoctest-2025.10.3.dist-info/WHEEL
pytest_bashdoctest-2025.10.3.dist-info/entry_points.txt
pytest_bashdoctest-2025.10.3.dist-info/licenses/LICENSE
pytest_bashdoctest-2025.10.3.dist-info/RECORD
