Metadata-Version: 2.4
Name: pytest-bashdoctest
Version: 2025.10.3
Summary: A pytest plugin for testing bash command examples in markdown documentation
Project-URL: Homepage, https://github.com/dnouri/pytest-bashdoctest
Project-URL: Documentation, https://github.com/dnouri/pytest-bashdoctest#readme
Project-URL: Repository, https://github.com/dnouri/pytest-bashdoctest
Project-URL: Issues, https://github.com/dnouri/pytest-bashdoctest/issues
Author-email: Daniel Nouri <daniel.nouri@gmail.com>
License: MIT
License-File: LICENSE
Keywords: bash,documentation,markdown,plugin,pytest,testing
Classifier: Development Status :: 4 - Beta
Classifier: Framework :: Pytest
Classifier: Intended Audience :: Developers
Classifier: License :: OSI Approved :: MIT License
Classifier: Operating System :: OS Independent
Classifier: Programming Language :: Python :: 3
Classifier: Programming Language :: Python :: 3.12
Classifier: Programming Language :: Python :: 3.13
Classifier: Topic :: Software Development :: Documentation
Classifier: Topic :: Software Development :: Testing
Requires-Python: >=3.12
Requires-Dist: pytest>=7.0.0
Provides-Extra: dev
Requires-Dist: pre-commit>=4.0.0; extra == 'dev'
Requires-Dist: pytest-cov>=4.0.0; extra == 'dev'
Requires-Dist: pytest>=7.0.0; extra == 'dev'
Requires-Dist: ruff>=0.1.0; extra == 'dev'
